experiment 10/HW10_403106092_ali_soltani_403106527_yeganeh_karbalaei_403106681_mohammadmahdi_moradi/quartus/stack_cpu.v
module stack_cpu (
    input  wire       clk,
    input  wire       reset,

    output reg  [7:0] memory_address,
    input  wire [7:0] memory_read_data,
    output reg  [7:0] memory_write_data,
    output reg        memory_write_enable
);

    // ------------------------------------------------------------
    // Opcodes
    // ------------------------------------------------------------

    localparam [3:0] OP_PUSHC = 4'b0000;
    localparam [3:0] OP_PUSH  = 4'b0001;
    localparam [3:0] OP_POP   = 4'b0010;
    localparam [3:0] OP_JUMP  = 4'b0011;
    localparam [3:0] OP_JZ    = 4'b0100;
    localparam [3:0] OP_JS    = 4'b0101;
    localparam [3:0] OP_ADD   = 4'b0110;
    localparam [3:0] OP_SUB   = 4'b0111;
    localparam [3:0] OP_SWAP  = 4'b1000;
    localparam [3:0] OP_SHL   = 4'b1001;
    localparam [3:0] OP_CMP   = 4'b1010;


    // ------------------------------------------------------------
    // FSM states
    // ------------------------------------------------------------

    localparam [3:0] STATE_FETCH         = 4'd0;
    localparam [3:0] STATE_DECODE        = 4'd1;
    localparam [3:0] STATE_FETCH_OPERAND = 4'd2;
    localparam [3:0] STATE_PUSHC         = 4'd3;
    localparam [3:0] STATE_PUSH          = 4'd4;
    localparam [3:0] STATE_POP           = 4'd5;
    localparam [3:0] STATE_JUMP          = 4'd6;
    localparam [3:0] STATE_JZ            = 4'd7;
    localparam [3:0] STATE_JS            = 4'd8;
    localparam [3:0] STATE_ADD           = 4'd9;
    localparam [3:0] STATE_SUB           = 4'd10;
    localparam [3:0] STATE_SWAP          = 4'd11;
    localparam [3:0] STATE_SHL           = 4'd12;
    localparam [3:0] STATE_CMP           = 4'd13;


    // ------------------------------------------------------------
    // CPU registers
    // ------------------------------------------------------------

    reg [7:0] program_counter;
    reg [7:0] instruction_register;
    reg [7:0] operand_register;

    reg [7:0] stack [0:7];
    reg [3:0] stack_pointer;

    reg zero_flag;
    reg sign_flag;

    reg [3:0] state;

    integer i;


    // ------------------------------------------------------------
    // Datapath signals
    // ------------------------------------------------------------

    wire [3:0] opcode;

    wire [7:0] stack_top;
    wire [7:0] stack_second;

    wire [7:0] add_result;
    wire [7:0] sub_result;


    assign opcode = instruction_register[3:0];

    // Stack pointer points to the next free location
    assign stack_top =
        (stack_pointer > 0)
        ? stack[stack_pointer - 4'd1]
        : 8'd0;

    assign stack_second =
        (stack_pointer > 1)
        ? stack[stack_pointer - 4'd2]
        : 8'd0;

    assign add_result = stack_second + stack_top;

    // SUB and CMP use B - A
    assign sub_result = stack_second - stack_top;


    // ------------------------------------------------------------
    // Memory interface
    // ------------------------------------------------------------

    always @(*) begin

        // Fetch instructions by default
        memory_address      = program_counter;
        memory_write_data   = 8'd0;
        memory_write_enable = 1'b0;

        case (state)

            STATE_PUSH: begin
                // Read data from memory or input port
                memory_address = operand_register;
            end

            STATE_POP: begin
                // Write stack top to memory or output port
                memory_address      = operand_register;
                memory_write_data   = stack_top;
                memory_write_enable = 1'b1;
            end

            default: begin
                memory_address = program_counter;
            end

        endcase
    end


    // ------------------------------------------------------------
    // Control unit
    // ------------------------------------------------------------

    always @(posedge clk or posedge reset) begin

        if (reset) begin

            program_counter     <= 8'd0;
            instruction_register <= 8'd0;
            operand_register     <= 8'd0;

            stack_pointer <= 4'd0;

            zero_flag <= 1'b0;
            sign_flag <= 1'b0;

            state <= STATE_FETCH;

            // Clear stack registers
            for (i = 0; i < 8; i = i + 1)
                stack[i] <= 8'd0;

        end

        else begin

            case (state)

                // ------------------------------------------------
                // Fetch instruction
                // ------------------------------------------------

                STATE_FETCH: begin

                    instruction_register <= memory_read_data;
                    program_counter <= program_counter + 8'd1;

                    state <= STATE_DECODE;

                end


                // ------------------------------------------------
                // Decode instruction
                // ------------------------------------------------

                STATE_DECODE: begin

                    case (opcode)

                        OP_PUSHC,
                        OP_PUSH,
                        OP_POP:
                            state <= STATE_FETCH_OPERAND;

                        OP_JUMP:
                            state <= STATE_JUMP;

                        OP_JZ:
                            state <= STATE_JZ;

                        OP_JS:
                            state <= STATE_JS;

                        OP_ADD:
                            state <= STATE_ADD;

                        OP_SUB:
                            state <= STATE_SUB;

                        OP_SWAP:
                            state <= STATE_SWAP;

                        OP_SHL:
                            state <= STATE_SHL;

                        OP_CMP:
                            state <= STATE_CMP;

                        default:
                            state <= STATE_FETCH;

                    endcase

                end


                // ------------------------------------------------
                // Fetch instruction operand
                // ------------------------------------------------

                STATE_FETCH_OPERAND: begin

                    operand_register <= memory_read_data;
                    program_counter <= program_counter + 8'd1;

                    case (opcode)

                        OP_PUSHC:
                            state <= STATE_PUSHC;

                        OP_PUSH:
                            state <= STATE_PUSH;

                        OP_POP:
                            state <= STATE_POP;

                        default:
                            state <= STATE_FETCH;

                    endcase

                end


                // ------------------------------------------------
                // PUSHC
                // ------------------------------------------------

                STATE_PUSHC: begin

                    stack[stack_pointer] <= operand_register;
                    stack_pointer <= stack_pointer + 4'd1;

                    state <= STATE_FETCH;

                end


                // ------------------------------------------------
                // PUSH
                // ------------------------------------------------

                STATE_PUSH: begin

                    stack[stack_pointer] <= memory_read_data;
                    stack_pointer <= stack_pointer + 4'd1;

                    state <= STATE_FETCH;

                end


                // ------------------------------------------------
                // POP
                // ------------------------------------------------

                STATE_POP: begin

                    // Memory write occurs through combinational interface
                    stack_pointer <= stack_pointer - 4'd1;

                    state <= STATE_FETCH;

                end


                // ------------------------------------------------
                // JUMP
                // ------------------------------------------------

                STATE_JUMP: begin

                    program_counter <= stack_top;
                    stack_pointer <= stack_pointer - 4'd1;

                    state <= STATE_FETCH;

                end


                // ------------------------------------------------
                // JZ
                // ------------------------------------------------

                STATE_JZ: begin

                    // Jump target is always removed from stack
                    if (zero_flag)
                        program_counter <= stack_top;

                    stack_pointer <= stack_pointer - 4'd1;

                    state <= STATE_FETCH;

                end


                // ------------------------------------------------
                // JS
                // ------------------------------------------------

                STATE_JS: begin

                    // Jump target is always removed from stack
                    if (sign_flag)
                        program_counter <= stack_top;

                    stack_pointer <= stack_pointer - 4'd1;

                    state <= STATE_FETCH;

                end


                // ------------------------------------------------
                // ADD
                // ------------------------------------------------

                STATE_ADD: begin

                    // Replace B and A with B + A
                    stack[stack_pointer - 4'd2] <= add_result;
                    stack_pointer <= stack_pointer - 4'd1;

                    // Update status flags
                    zero_flag <= (add_result == 8'd0);
                    sign_flag <= add_result[7];

                    state <= STATE_FETCH;

                end


                // ------------------------------------------------
                // SUB
                // ------------------------------------------------

                STATE_SUB: begin

                    // Replace B and A with B - A
                    stack[stack_pointer - 4'd2] <= sub_result;
                    stack_pointer <= stack_pointer - 4'd1;

                    // Update status flags
                    zero_flag <= (sub_result == 8'd0);
                    sign_flag <= sub_result[7];

                    state <= STATE_FETCH;

                end


                // ------------------------------------------------
                // SWAP
                // ------------------------------------------------

                STATE_SWAP: begin

                    // Exchange the top two stack elements
                    stack[stack_pointer - 4'd1]
                        <= stack[stack_pointer - 4'd2];

                    stack[stack_pointer - 4'd2]
                        <= stack[stack_pointer - 4'd1];

                    state <= STATE_FETCH;

                end


                // ------------------------------------------------
                // SHL
                // ------------------------------------------------

                STATE_SHL: begin

                    // Shift stack top left by one bit
                    stack[stack_pointer - 4'd1]
                        <= stack_top << 1;

                    state <= STATE_FETCH;

                end


                // ------------------------------------------------
                // CMP
                // ------------------------------------------------

                STATE_CMP: begin

                    // Compare B and A without modifying stack
                    zero_flag <= (sub_result == 8'd0);
                    sign_flag <= sub_result[7];

                    state <= STATE_FETCH;

                end


                // ------------------------------------------------
                // Recovery
                // ------------------------------------------------

                default: begin
                    state <= STATE_FETCH;
                end

            endcase

        end

    end

endmodule

experiment 10/HW10_403106092_ali_soltani_403106527_yeganeh_karbalaei_403106681_mohammadmahdi_moradi/quartus/stack_cpu_tb.v
`timescale 1ns/1ps

module stack_cpu_tb;

    reg clk;
    reg reset;

    wire [7:0] memory_address;
    reg  [7:0] memory [0:255];
    wire [7:0] memory_read_data;
    wire [7:0] memory_write_data;
    wire       memory_write_enable;

    integer i;
    integer passed_tests;
    integer failed_tests;


    // ------------------------------------------------------------
    // DUT
    // ------------------------------------------------------------

    stack_cpu dut (
        .clk                 (clk),
        .reset               (reset),
        .memory_address      (memory_address),
        .memory_read_data    (memory_read_data),
        .memory_write_data   (memory_write_data),
        .memory_write_enable (memory_write_enable)
    );


    // ------------------------------------------------------------
    // Simple memory model
    // ------------------------------------------------------------

    assign memory_read_data = memory[memory_address];

    always @(posedge clk) begin
        if (memory_write_enable)
            memory[memory_address] <= memory_write_data;
    end


    // ------------------------------------------------------------
    // Clock
    // ------------------------------------------------------------

    initial begin
        clk = 1'b0;
        forever #5 clk = ~clk;
    end


    // ------------------------------------------------------------
    // Utility tasks
    // ------------------------------------------------------------

    task clear_memory;
        begin
            for (i = 0; i < 256; i = i + 1)
                memory[i] = 8'h00;
        end
    endtask


    task start_cpu;
        begin
            reset = 1'b1;

            repeat (2)
                @(posedge clk);

            @(negedge clk);
            reset = 1'b0;
        end
    endtask


    task wait_for_fetch;
        input [7:0] expected_pc;

        integer timeout;

        begin
            timeout = 0;

            while (
                !((dut.state == 4'd0) &&
                  (dut.program_counter == expected_pc))
                &&
                (timeout < 100)
            ) begin
                @(posedge clk);
                #1;
                timeout = timeout + 1;
            end

            if (timeout >= 100) begin
                $display(
                    "ERROR: Timeout waiting for PC = %02h",
                    expected_pc
                );

                failed_tests = failed_tests + 1;
            end
        end
    endtask


    // ------------------------------------------------------------
    // SWAP test
    // ------------------------------------------------------------

    task test_swap;
        begin
            $display("\n--- SWAP test ---");

            reset = 1'b1;
            clear_memory();

            // PUSHC 12
            memory[8'h00] = 8'h00;
            memory[8'h01] = 8'h12;

            // PUSHC A5
            memory[8'h02] = 8'h00;
            memory[8'h03] = 8'hA5;

            // SWAP
            memory[8'h04] = 8'h08;

            start_cpu();

            wait_for_fetch(8'h05);

            if (
                (dut.stack_pointer == 4'd2) &&
                (dut.stack[0] == 8'hA5) &&
                (dut.stack[1] == 8'h12)
            ) begin

                $display("PASS: SWAP");
                passed_tests = passed_tests + 1;

            end
            else begin

                $display(
                    "FAIL: SWAP | stack[0]=%02h stack[1]=%02h SP=%0d",
                    dut.stack[0],
                    dut.stack[1],
                    dut.stack_pointer
                );

                failed_tests = failed_tests + 1;

            end
        end
    endtask


    // ------------------------------------------------------------
    // SHL test
    // ------------------------------------------------------------

    task test_shl;
        input [7:0] input_value;
        input [7:0] expected_value;

        begin
            reset = 1'b1;
            clear_memory();

            // PUSHC input_value
            memory[8'h00] = 8'h00;
            memory[8'h01] = input_value;

            // SHL
            memory[8'h02] = 8'h09;

            start_cpu();

            wait_for_fetch(8'h03);

            if (
                (dut.stack_pointer == 4'd1) &&
                (dut.stack[0] == expected_value)
            ) begin

                $display(
                    "PASS: SHL %0d -> %0d",
                    input_value,
                    expected_value
                );

                passed_tests = passed_tests + 1;

            end
            else begin

                $display(
                    "FAIL: SHL %0d | expected=%0d actual=%0d",
                    input_value,
                    expected_value,
                    dut.stack[0]
                );

                failed_tests = failed_tests + 1;

            end
        end
    endtask


    // ------------------------------------------------------------
    // CMP test
    // ------------------------------------------------------------

    task test_cmp;
        input [7:0] value_b;
        input [7:0] value_a;
        input       expected_zero;
        input       expected_sign;

        begin
            reset = 1'b1;
            clear_memory();

            // Push B first
            memory[8'h00] = 8'h00;
            memory[8'h01] = value_b;

            // Push A second
            memory[8'h02] = 8'h00;
            memory[8'h03] = value_a;

            // CMP -> B - A
            memory[8'h04] = 8'h0A;

            start_cpu();

            wait_for_fetch(8'h05);

            if (
                (dut.stack_pointer == 4'd2) &&
                (dut.stack[0] == value_b) &&
                (dut.stack[1] == value_a) &&
                (dut.zero_flag == expected_zero) &&
                (dut.sign_flag == expected_sign)
            ) begin

                $display(
                    "PASS: CMP B=%0d A=%0d | Z=%b S=%b",
                    value_b,
                    value_a,
                    dut.zero_flag,
                    dut.sign_flag
                );

                passed_tests = passed_tests + 1;

            end
            else begin

                $display(
                    "FAIL: CMP B=%0d A=%0d | Z=%b S=%b SP=%0d",
                    value_b,
                    value_a,
                    dut.zero_flag,
                    dut.sign_flag,
                    dut.stack_pointer
                );

                failed_tests = failed_tests + 1;

            end
        end
    endtask


    // ------------------------------------------------------------
    // Test sequence
    // ------------------------------------------------------------

    initial begin

        reset = 1'b1;

        passed_tests = 0;
        failed_tests = 0;

        clear_memory();


        // SWAP
        test_swap();


        // SHL mandatory values
        $display("\n--- SHL tests ---");

        test_shl(8'd0,   8'd0);
        test_shl(8'd1,   8'd2);
        test_shl(8'd63,  8'd126);
        test_shl(8'd127, 8'd254);


        // CMP mandatory conditions
        $display("\n--- CMP tests ---");

        // B < A
        test_cmp(
            8'd5,
            8'd9,
            1'b0,
            1'b1
        );

        // B = A
        test_cmp(
            8'd7,
            8'd7,
            1'b1,
            1'b0
        );

        // B > A
        test_cmp(
            8'd9,
            8'd5,
            1'b0,
            1'b0
        );


        // --------------------------------------------------------
        // Summary
        // --------------------------------------------------------

        $display("\n================================");
        $display("CPU TEST SUMMARY");
        $display("Passed: %0d", passed_tests);
        $display("Failed: %0d", failed_tests);
        $display("================================");

        if (failed_tests == 0)
            $display("ALL CPU TESTS PASSED");
        else
            $display("CPU TESTS FAILED");

        #20;
        $finish;

    end


    // ------------------------------------------------------------
    // Waveform
    // ------------------------------------------------------------

    initial begin
        $dumpfile("stack_cpu_tb.vcd");
        $dumpvars(0, stack_cpu_tb);
    end

endmodule

experiment 10/HW10_403106092_ali_soltani_403106527_yeganeh_karbalaei_403106681_mohammadmahdi_moradi/quartus/stack_cpu_tb.vcd
$date
	Sat Sep 12 12:14:20 2026
$end
$version
	Icarus Verilog
$end
$timescale
	1ps
$end
$scope module stack_cpu_tb $end
$var wire 8 ! memory_read_data [7:0] $end
$var wire 1 " memory_write_enable $end
$var wire 8 # memory_write_data [7:0] $end
$var wire 8 $ memory_address [7:0] $end
$var reg 1 % clk $end
$var reg 1 & reset $end
$var integer 32 ' failed_tests [31:0] $end
$var integer 32 ( i [31:0] $end
$var integer 32 ) passed_tests [31:0] $end
$scope module dut $end
$var wire 1 % clk $end
$var wire 8 * memory_read_data [7:0] $end
$var wire 1 & reset $end
$var wire 8 + sub_result [7:0] $end
$var wire 8 , stack_top [7:0] $end
$var wire 8 - stack_second [7:0] $end
$var wire 4 . opcode [3:0] $end
$var wire 8 / add_result [7:0] $end
$var parameter 4 0 OP_ADD $end
$var parameter 4 1 OP_CMP $end
$var parameter 4 2 OP_JS $end
$var parameter 4 3 OP_JUMP $end
$var parameter 4 4 OP_JZ $end
$var parameter 4 5 OP_POP $end
$var parameter 4 6 OP_PUSH $end
$var parameter 4 7 OP_PUSHC $end
$var parameter 4 8 OP_SHL $end
$var parameter 4 9 OP_SUB $end
$var parameter 4 : OP_SWAP $end
$var parameter 4 ; STATE_ADD $end
$var parameter 4 < STATE_CMP $end
$var parameter 4 = STATE_DECODE $end
$var parameter 4 > STATE_FETCH $end
$var parameter 4 ? STATE_FETCH_OPERAND $end
$var parameter 4 @ STATE_JS $end
$var parameter 4 A STATE_JUMP $end
$var parameter 4 B STATE_JZ $end
$var parameter 4 C STATE_POP $end
$var parameter 4 D STATE_PUSH $end
$var parameter 4 E STATE_PUSHC $end
$var parameter 4 F STATE_SHL $end
$var parameter 4 G STATE_SUB $end
$var parameter 4 H STATE_SWAP $end
$var reg 8 I instruction_register [7:0] $end
$var reg 8 J memory_address [7:0] $end
$var reg 8 K memory_write_data [7:0] $end
$var reg 1 " memory_write_enable $end
$var reg 8 L operand_register [7:0] $end
$var reg 8 M program_counter [7:0] $end
$var reg 1 N sign_flag $end
$var reg 4 O stack_pointer [3:0] $end
$var reg 4 P state [3:0] $end
$var reg 1 Q zero_flag $end
$var integer 32 R i [31:0] $end
$upscope $end
$scope task clear_memory $end
$upscope $end
$scope task start_cpu $end
$upscope $end
$scope task test_cmp $end
$var reg 1 S expected_sign $end
$var reg 1 T expected_zero $end
$var reg 8 U value_a [7:0] $end
$var reg 8 V value_b [7:0] $end
$upscope $end
$scope task test_shl $end
$var reg 8 W expected_value [7:0] $end
$var reg 8 X input_value [7:0] $end
$upscope $end
$scope task test_swap $end
$upscope $end
$scope task wait_for_fetch $end
$var reg 8 Y expected_pc [7:0] $end
$var integer 32 Z timeout [31:0] $end
$upscope $end
$upscope $end
$enddefinitions $end
$comment Show the parameter values. $end
$dumpall
b1011 H
b1010 G
b1100 F
b11 E
b100 D
b101 C
b111 B
b110 A
b1000 @
b10 ?
b0 >
b1 =
b1101 <
b1001 ;
b1000 :
b111 9
b1001 8
b0 7
b1 6
b10 5
b100 4
b11 3
b101 2
b1010 1
b110 0
$end
#0
$dumpvars
bx Z
bx Y
bx X
bx W
bx V
bx U
xT
xS
b1000 R
0Q
b0 P
b0 O
0N
b0 M
b0 L
b0 K
b0 J
b0 I
b0 /
b0 .
b0 -
b0 ,
b0 +
b0 *
b0 )
b100000000 (
b0 '
1&
0%
b0 $
b0 #
0"
b0 !
$end
#5000
b1000 R
1%
#10000
0%
#15000
b1000 R
1%
#20000
b0 Z
b101 Y
0&
0%
#25000
b10010 !
b10010 *
b1 $
b1 J
b1 P
b1 M
1%
#26000
b1 Z
#30000
0%
#35000
b10 P
1%
#36000
b10 Z
#40000
0%
#45000
b0 !
b0 *
b10 $
b10 J
b11 P
b10 M
b10010 L
1%
#46000
b11 Z
#50000
0%
#55000
b10010 /
b11101110 +
b10010 ,
b0 P
b1 O
1%
#56000
b100 Z
#60000
0%
#65000
b10100101 !
b10100101 *
b11 $
b11 J
b1 P
b11 M
1%
#66000
b101 Z
#70000
0%
#75000
b10 P
1%
#76000
b110 Z
#80000
0%
#85000
b1000 !
b1000 *
b100 $
b100 J
b11 P
b100 M
b10100101 L
1%
#86000
b111 Z
#90000
0%
#95000
b10100101 ,
b10110111 /
b1101101 +
b10010 -
b0 P
b10 O
1%
#96000
b1000 Z
#100000
0%
#105000
b0 !
b0 *
b101 $
b101 J
b1000 .
b1 P
b101 M
b1000 I
1%
#106000
b1001 Z
#110000
0%
#115000
b1011 P
1%
#116000
b1010 Z
#120000
0%
#125000
b10100101 -
b10110111 /
b10010011 +
b10010 ,
b0 P
1%
#126000
b0 ,
b0 /
b0 +
b0 -
b0 .
b0 $
b0 J
b0 O
b0 L
b0 I
b0 M
b1000 R
b100000000 (
1&
b0 W
b0 X
b1 )
b1011 Z
#130000
0%
#135000
b1000 R
1%
#140000
0%
#145000
b1000 R
1%
#150000
b0 Z
b11 Y
0&
0%
#155000
b1 $
b1 J
b1 P
b1 M
1%
#156000
b1 Z
#160000
0%
#165000
b10 P
1%
#166000
b10 Z
#170000
0%
#175000
b1001 !
b1001 *
b10 $
b10 J
b11 P
b10 M
1%
#176000
b11 Z
#180000
0%
#185000
b0 P
b1 O
1%
#186000
b100 Z
#190000
0%
#195000
b0 !
b0 *
b11 $
b11 J
b1001 .
b1 P
b11 M
b1001 I
1%
#196000
b101 Z
#200000
0%
#205000
b1100 P
1%
#206000
b110 Z
#210000
0%
#215000
b0 P
1%
#216000
b0 .
b0 $
b0 J
b0 O
b0 I
b0 M
b1000 R
b100000000 (
1&
b10 W
b1 X
b10 )
b111 Z
#220000
0%
#225000
b1000 R
1%
#230000
0%
#235000
b1000 R
1%
#240000
b0 Z
0&
0%
#245000
b1 !
b1 *
b1 $
b1 J
b1 P
b1 M
1%
#246000
b1 Z
#250000
0%
#255000
b10 P
1%
#256000
b10 Z
#260000
0%
#265000
b1001 !
b1001 *
b10 $
b10 J
b11 P
b10 M
b1 L
1%
#266000
b11 Z
#270000
0%
#275000
b1 /
b11111111 +
b1 ,
b0 P
b1 O
1%
#276000
b100 Z
#280000
0%
#285000
b0 !
b0 *
b11 $
b11 J
b1001 .
b1 P
b11 M
b1001 I
1%
#286000
b101 Z
#290000
0%
#295000
b1100 P
1%
#296000
b110 Z
#300000
0%
#305000
b10 /
b11111110 +
b10 ,
b0 P
1%
#306000
b0 /
b0 +
b0 ,
b0 .
b0 $
b0 J
b0 O
b0 L
b0 I
b0 M
b1000 R
b100000000 (
1&
b1111110 W
b111111 X
b11 )
b111 Z
#310000
0%
#315000
b1000 R
1%
#320000
0%
#325000
b1000 R
1%
#330000
b0 Z
0&
0%
#335000
b111111 !
b111111 *
b1 $
b1 J
b1 P
b1 M
1%
#336000
b1 Z
#340000
0%
#345000
b10 P
1%
#346000
b10 Z
#350000
0%
#355000
b1001 !
b1001 *
b10 $
b10 J
b11 P
b10 M
b111111 L
1%
#356000
b11 Z
#360000
0%
#365000
b111111 /
b11000001 +
b111111 ,
b0 P
b1 O
1%
#366000
b100 Z
#370000
0%
#375000
b0 !
b0 *
b11 $
b11 J
b1001 .
b1 P
b11 M
b1001 I
1%
#376000
b101 Z
#380000
0%
#385000
b1100 P
1%
#386000
b110 Z
#390000
0%
#395000
b1111110 /
b10000010 +
b1111110 ,
b0 P
1%
#396000
b0 /
b0 +
b0 ,
b0 .
b0 $
b0 J
b0 O
b0 L
b0 I
b0 M
b1000 R
b100000000 (
1&
b11111110 W
b1111111 X
b100 )
b111 Z
#400000
0%
#405000
b1000 R
1%
#410000
0%
#415000
b1000 R
1%
#420000
b0 Z
0&
0%
#425000
b1111111 !
b1111111 *
b1 $
b1 J
b1 P
b1 M
1%
#426000
b1 Z
#430000
0%
#435000
b10 P
1%
#436000
b10 Z
#440000
0%
#445000
b1001 !
b1001 *
b10 $
b10 J
b11 P
b10 M
b1111111 L
1%
#446000
b11 Z
#450000
0%
#455000
b1111111 /
b10000001 +
b1111111 ,
b0 P
b1 O
1%
#456000
b100 Z
#460000
0%
#465000
b0 !
b0 *
b11 $
b11 J
b1001 .
b1 P
b11 M
b1001 I
1%
#466000
b101 Z
#470000
0%
#475000
b1100 P
1%
#476000
b110 Z
#480000
0%
#485000
b11111110 /
b10 +
b11111110 ,
b0 P
1%
#486000
b0 /
b0 +
b0 ,
b0 .
b0 $
b0 J
b0 O
b0 L
b0 I
b0 M
b1000 R
b0 !
b0 *
b100000000 (
1&
1S
0T
b1001 U
b101 V
b101 )
b111 Z
#490000
0%
#495000
b1000 R
1%
#500000
0%
#505000
b1000 R
1%
#510000
b0 Z
b101 Y
0&
0%
#515000
b101 !
b101 *
b1 $
b1 J
b1 P
b1 M
1%
#516000
b1 Z
#520000
0%
#525000
b10 P
1%
#526000
b10 Z
#530000
0%
#535000
b0 !
b0 *
b10 $
b10 J
b11 P
b10 M
b101 L
1%
#536000
b11 Z
#540000
0%
#545000
b101 /
b11111011 +
b101 ,
b0 P
b1 O
1%
#546000
b100 Z
#550000
0%
#555000
b1001 !
b1001 *
b11 $
b11 J
b1 P
b11 M
1%
#556000
b101 Z
#560000
0%
#565000
b10 P
1%
#566000
b110 Z
#570000
0%
#575000
b1010 !
b1010 *
b100 $
b100 J
b11 P
b100 M
b1001 L
1%
#576000
b111 Z
#580000
0%
#585000
b1001 ,
b1110 /
b11111100 +
b101 -
b0 P
b10 O
1%
#586000
b1000 Z
#590000
0%
#595000
b0 !
b0 *
b101 $
b101 J
b1010 .
b1 P
b101 M
b1010 I
1%
#596000
b1001 Z
#600000
0%
#605000
b1101 P
1%
#606000
b1010 Z
#610000
0%
#615000
b0 P
1N
1%
#616000
b0 ,
b0 /
b0 +
b0 -
b0 .
b0 $
b0 J
0N
b0 O
b0 L
b0 I
b0 M
b1000 R
b100000000 (
1&
0S
1T
b111 U
b111 V
b110 )
b1011 Z
#620000
0%
#625000
b1000 R
1%
#630000
0%
#635000
b1000 R
1%
#640000
b0 Z
0&
0%
#645000
b111 !
b111 *
b1 $
b1 J
b1 P
b1 M
1%
#646000
b1 Z
#650000
0%
#655000
b10 P
1%
#656000
b10 Z
#660000
0%
#665000
b0 !
b0 *
b10 $
b10 J
b11 P
b10 M
b111 L
1%
#666000
b11 Z
#670000
0%
#675000
b111 /
b11111001 +
b111 ,
b0 P
b1 O
1%
#676000
b100 Z
#680000
0%
#685000
b111 !
b111 *
b11 $
b11 J
b1 P
b11 M
1%
#686000
b101 Z
#690000
0%
#695000
b10 P
1%
#696000
b110 Z
#700000
0%
#705000
b1010 !
b1010 *
b100 $
b100 J
b11 P
b100 M
1%
#706000
b111 Z
#710000
0%
#715000
b1110 /
b0 +
b111 -
b0 P
b10 O
1%
#716000
b1000 Z
#720000
0%
#725000
b0 !
b0 *
b101 $
b101 J
b1010 .
b1 P
b101 M
b1010 I
1%
#726000
b1001 Z
#730000
0%
#735000
b1101 P
1%
#736000
b1010 Z
#740000
0%
#745000
b0 P
1Q
1%
#746000
b0 ,
b0 /
b0 +
b0 -
b0 .
b0 $
b0 J
0Q
b0 O
b0 L
b0 I
b0 M
b1000 R
b100000000 (
1&
0T
b101 U
b1001 V
b111 )
b1011 Z
#750000
0%
#755000
b1000 R
1%
#760000
0%
#765000
b1000 R
1%
#770000
b0 Z
0&
0%
#775000
b1001 !
b1001 *
b1 $
b1 J
b1 P
b1 M
1%
#776000
b1 Z
#780000
0%
#785000
b10 P
1%
#786000
b10 Z
#790000
0%
#795000
b0 !
b0 *
b10 $
b10 J
b11 P
b10 M
b1001 L
1%
#796000
b11 Z
#800000
0%
#805000
b1001 /
b11110111 +
b1001 ,
b0 P
b1 O
1%
#806000
b100 Z
#810000
0%
#815000
b101 !
b101 *
b11 $
b11 J
b1 P
b11 M
1%
#816000
b101 Z
#820000
0%
#825000
b10 P
1%
#826000
b110 Z
#830000
0%
#835000
b1010 !
b1010 *
b100 $
b100 J
b11 P
b100 M
b101 L
1%
#836000
b111 Z
#840000
0%
#845000
b101 ,
b1110 /
b100 +
b1001 -
b0 P
b10 O
1%
#846000
b1000 Z
#850000
0%
#855000
b0 !
b0 *
b101 $
b101 J
b1010 .
b1 P
b101 M
b1010 I
1%
#856000
b1001 Z
#860000
0%
#865000
b1101 P
1%
#866000
b1010 Z
#870000
0%
#875000
b0 P
1%
#876000
b1000 )
b1011 Z
#880000
0%
#885000
b110 $
b110 J
b0 .
b1 P
b110 M
b0 I
1%
#890000
0%
#895000
b10 P
1%
